AUTHORS.rst
CONTRIBUTING.rst
HISTORY.rst
LICENSE
MANIFEST.in
README.rst
setup.cfg
setup.py
docs/Makefile
docs/authors.rst
docs/conf.py
docs/contributing.rst
docs/history.rst
docs/index.rst
docs/installation.rst
docs/make.bat
docs/readme.rst
docs/usage.rst
tangle/__init__.py
tangle/m_aspect.py
tangle/m_bean.py
tangle/m_container.py
tangle/m_context.py
tangle/m_event.py
tangle/m_factory.py
tangle/m_support.py
tangle/m_tangle.py
tangle.egg-info/PKG-INFO
tangle.egg-info/SOURCES.txt
tangle.egg-info/dependency_links.txt
tangle.egg-info/not-zip-safe
tangle.egg-info/requires.txt
tangle.egg-info/top_level.txt
tests/__init__.py
tests/test_aspect.py
tests/test_bean.py
tests/test_beanconfig.py
tests/test_commons.py
tests/test_container.py