Metadata-Version: 1.1
Name: tangle
Version: 0.1.0
Summary: Python framework with DI, AOP support
Home-page: https://github.com/fifman/tangle
Author: Fifman Feng
Author-email: fifman@163.com
License: MIT license
Keywords: tangle
Platform: UNKNOWN
Classifier: Development Status :: 2 - Pre-Alpha
Classifier: Intended Audience :: Developers
Classifier: License :: OSI Approved :: MIT License
Classifier: Natural Language :: English
Classifier: Programming Language :: Python :: 2
Classifier: Programming Language :: Python :: 2.7
Classifier: Programming Language :: Python :: 3
Classifier: Programming Language :: Python :: 3.4
Classifier: Programming Language :: Python :: 3.5
Classifier: Programming Language :: Python :: 3.6
